<?xml version="1.0" ?><annotation>
		<folder>VOC</folder>
		<filename>30001020115510862331</filename>
		<object_num>3</object_num>
		<size>
			<width>500</width>
			<height>350</height>
			<depth>3</depth>
		</size>
		<object>
			<name>2</name>
			<difficult>0</difficult>
			<pose>Frontal</pose>
			<truncated>0</truncated>
			<bndbox>
				<xmin>241</xmin>
				<ymin>189</ymin>
				<xmax>353</xmax>
				<ymax>300</ymax>
			</bndbox>
		</object>
		<object>
			<name>5</name>
			<difficult>0</difficult>
			<pose>Frontal</pose>
			<truncated>0</truncated>
			<bndbox>
				<xmin>288</xmin>
				<ymin>70</ymin>
				<xmax>426</xmax>
				<ymax>208</ymax>
			</bndbox>
		</object>
		<object>
			<name>5</name>
			<difficult>0</difficult>
			<pose>Frontal</pose>
			<truncated>0</truncated>
			<bndbox>
				<xmin>150</xmin>
				<ymin>91</ymin>
				<xmax>278</xmax>
				<ymax>220</ymax>
			</bndbox>
		</object>
	</annotation>