<?xml version="1.0" ?><annotation>
		<folder>VOC</folder>
		<filename>30001020215508915351</filename>
		<object_num>3</object_num>
		<size>
			<width>500</width>
			<height>350</height>
			<depth>3</depth>
		</size>
		<object>
			<name>2</name>
			<difficult>0</difficult>
			<pose>Frontal</pose>
			<truncated>0</truncated>
			<bndbox>
				<xmin>316</xmin>
				<ymin>163</ymin>
				<xmax>434</xmax>
				<ymax>280</ymax>
			</bndbox>
		</object>
		<object>
			<name>8</name>
			<difficult>0</difficult>
			<pose>Frontal</pose>
			<truncated>0</truncated>
			<bndbox>
				<xmin>82</xmin>
				<ymin>141</ymin>
				<xmax>243</xmax>
				<ymax>310</ymax>
			</bndbox>
		</object>
		<object>
			<name>9</name>
			<difficult>0</difficult>
			<pose>Frontal</pose>
			<truncated>0</truncated>
			<bndbox>
				<xmin>120</xmin>
				<ymin>51</ymin>
				<xmax>325</xmax>
				<ymax>177</ymax>
			</bndbox>
		</object>
	</annotation>