<?xml version="1.0" ?><annotation>
		<folder>VOC</folder>
		<filename>30001020215508963671</filename>
		<object_num>3</object_num>
		<size>
			<width>500</width>
			<height>350</height>
			<depth>3</depth>
		</size>
		<object>
			<name>2</name>
			<difficult>0</difficult>
			<pose>Frontal</pose>
			<truncated>0</truncated>
			<bndbox>
				<xmin>248</xmin>
				<ymin>0</ymin>
				<xmax>364</xmax>
				<ymax>110</ymax>
			</bndbox>
		</object>
		<object>
			<name>2</name>
			<difficult>0</difficult>
			<pose>Frontal</pose>
			<truncated>0</truncated>
			<bndbox>
				<xmin>88</xmin>
				<ymin>65</ymin>
				<xmax>210</xmax>
				<ymax>187</ymax>
			</bndbox>
		</object>
		<object>
			<name>9</name>
			<difficult>0</difficult>
			<pose>Frontal</pose>
			<truncated>0</truncated>
			<bndbox>
				<xmin>208</xmin>
				<ymin>102</ymin>
				<xmax>417</xmax>
				<ymax>225</ymax>
			</bndbox>
		</object>
	</annotation>