<?xml version="1.0" ?><annotation>
		<folder>VOC</folder>
		<filename>30001020215509772601</filename>
		<object_num>2</object_num>
		<size>
			<width>500</width>
			<height>350</height>
			<depth>3</depth>
		</size>
		<object>
			<name>2</name>
			<difficult>0</difficult>
			<pose>Frontal</pose>
			<truncated>0</truncated>
			<bndbox>
				<xmin>147</xmin>
				<ymin>68</ymin>
				<xmax>270</xmax>
				<ymax>191</ymax>
			</bndbox>
		</object>
		<object>
			<name>5</name>
			<difficult>0</difficult>
			<pose>Frontal</pose>
			<truncated>0</truncated>
			<bndbox>
				<xmin>190</xmin>
				<ymin>143</ymin>
				<xmax>341</xmax>
				<ymax>293</ymax>
			</bndbox>
		</object>
	</annotation>