<?xml version="1.0" ?><annotation>
		<folder>VOC</folder>
		<filename>30001020115510014411</filename>
		<object_num>2</object_num>
		<size>
			<width>500</width>
			<height>350</height>
			<depth>3</depth>
		</size>
		<object>
			<name>2</name>
			<difficult>0</difficult>
			<pose>Frontal</pose>
			<truncated>0</truncated>
			<bndbox>
				<xmin>252</xmin>
				<ymin>87</ymin>
				<xmax>363</xmax>
				<ymax>199</ymax>
			</bndbox>
		</object>
		<object>
			<name>5</name>
			<difficult>0</difficult>
			<pose>Frontal</pose>
			<truncated>0</truncated>
			<bndbox>
				<xmin>73</xmin>
				<ymin>65</ymin>
				<xmax>219</xmax>
				<ymax>211</ymax>
			</bndbox>
		</object>
	</annotation>